amplicnv/__init__.py
amplicnv/bedloader/__init__.py
amplicnv/bedloader/bedloader.py
amplicnv/checkmemory/__init__.py
amplicnv/checkmemory/checkmemory.py
amplicnv/cnvdetector/__init__.py
amplicnv/cnvdetector/cnvdetector.py
amplicnv/commons/__init__.py
amplicnv/commons/commons.py
amplicnv/data/cytoBand.txt
amplicnv/graphics/__init__.py
amplicnv/graphics/graphics.py
amplicnv/ideogram/__init__.py
amplicnv/ideogram/ideogram.py
amplicnv/mphandler/__init__.py
amplicnv/mphandler/mphandler.py
amplicnv/nrrhandler/__init__.py
amplicnv/nrrhandler/nrrhandler.py
amplicnv/stats/__init__.py
amplicnv/stats/stats.py
amplicnv/tsvparser/__init__.py
amplicnv/tsvparser/tsvparser.py
amplicnv/utils/__init__.py
amplicnv/utils/utils.py
amplicnv/vcfhandler/__init__.py
amplicnv/vcfhandler/vcfhandler.py
amplicnv/wrapper/__init__.py
amplicnv/wrapper/argdesc.py
amplicnv/wrapper/command_line.py
amplicnv/wrapper/utils.py
amplicnv-1.0.0b6.dist-info/LICENSE
amplicnv-1.0.0b6.dist-info/METADATA
amplicnv-1.0.0b6.dist-info/WHEEL
amplicnv-1.0.0b6.dist-info/entry_points.txt
amplicnv-1.0.0b6.dist-info/top_level.txt
amplicnv-1.0.0b6.dist-info/RECORD
